revision_gcs/__init__.py
revision_gcs/client.py
revision_gcs-0.0.7.dist-info/DESCRIPTION.rst
revision_gcs-0.0.7.dist-info/METADATA
revision_gcs-0.0.7.dist-info/RECORD
revision_gcs-0.0.7.dist-info/WHEEL
revision_gcs-0.0.7.dist-info/metadata.json
revision_gcs-0.0.7.dist-info/top_level.txt
