Metadata-Version: 2.0
Name: revision-gcs
Version: 0.0.7
Summary: Google Cloud Storage for Revision
Home-page: https://github.com/COLORFULBOARD/revision-gcs
Author: SENSY Inc.
Author-email: UNKNOWN
License: MIT
Platform: UNKNOWN
Classifier: Development Status :: 4 - Beta
Classifier: Environment :: Web Environment
Classifier: License :: OSI Approved :: MIT License
Classifier: Operating System :: OS Independent
Classifier: Programming Language :: Python
Classifier: Programming Language :: Python :: 2
Classifier: Programming Language :: Python :: 2.7
Classifier: Topic :: Software Development :: Libraries :: Python Modules
Requires-Dist: revision
Requires-Dist: google-cloud-storage (==1.6.0)
Provides-Extra: dev
Requires-Dist: flake8 (==3.5.0); extra == 'dev'
Requires-Dist: pytest (==3.3.1); extra == 'dev'
